Metadata-Version: 2.2
Name: hack4u_rixon
Version: 0.1.33
Summary: Una biblioteca para consultar los cursos de hack4u
Home-page: https://hack4u.io
Author: Rixon huaman
Dynamic: author
Dynamic: description
Dynamic: description-content-type
Dynamic: home-page
Dynamic: summary
